xlFormulas/__init__.py
xl_formulas-0.0.1.dist-info/LICENSE
xl_formulas-0.0.1.dist-info/METADATA
xl_formulas-0.0.1.dist-info/WHEEL
xl_formulas-0.0.1.dist-info/top_level.txt
xl_formulas-0.0.1.dist-info/RECORD
