Metadata-Version: 2.1
Name: xl-formulas
Version: 0.0.1
Summary: Helper to save Excel formulas from Pandas dataframes
Home-page: https://github.com/joetats/xlFormulas
Author: Joe Tatusko
Author-email: tatuskojc@gmail.com
License: UNKNOWN
Platform: UNKNOWN
Classifier: Programming Language :: Python :: 3
Classifier: License :: OSI Approved :: MIT License
Classifier: Operating System :: OS Independent
Classifier: Development Status :: 3 - Alpha
